{
    "niv": {
        "branch": "master",
        "description": "Easy dependency management for Nix projects",
        "homepage": "https://github.com/nmattia/niv",
        "owner": "nmattia",
        "repo": "niv",
        "rev": "9d35b9e4837ab88517210b1701127612c260eccf",
        "sha256": "0q50xhnm8g2yfyakrh0nly4swyygxpi0a8cb9gp65wcakcgvzvdh",
        "type": "tarball",
        "url": "https://github.com/nmattia/niv/archive/9d35b9e4837ab88517210b1701127612c260eccf.tar.gz",
        "url_template": "https://github.com/<owner>/<repo>/archive/<rev>.tar.gz"
    },
    "nixpkgs": {
        "branch": "nixpkgs-unstable",
        "description": "Nix Packages collection",
        "homepage": "",
        "owner": "NixOS",
        "repo": "nixpkgs",
        "rev": "2da96f3f9c44cf87e07387321f4ca406c1a8bb7e",
        "sha256": "03d0iym6m5kbp11lz5jcaf2627cqvry0lzmrmf6gmqvvfcal9vdl",
        "type": "tarball",
        "url": "https://github.com/NixOS/nixpkgs/archive/2da96f3f9c44cf87e07387321f4ca406c1a8bb7e.tar.gz",
        "url_template": "https://github.com/<owner>/<repo>/archive/<rev>.tar.gz"
    }
}
